{"snapshots": [{"funds": 10000, "stocksHeld": [{"name": "ADBE", "amount": 0, "value": 0.0}, {"name": "MSFT", "amount": 0, "value": 0.0}, {"name": "AVGO", "amount": 0, "value": 0.0}, {"name": "AMZN", "amount": 0, "value": 0.0}], "date": "2015-03-11"}, {"funds": 10000, "stocksHeld": [{"name": "ADBE", "amount": 0, "value": 0.0}, {"name": "MSFT", "amount": 0, "value": 0.0}, {"name": "AVGO", "amount": 0, "value": 0.0}, {"name": "AMZN", "amount": 0, "value": 0.0}], "date": "2015-03-11"}, {"funds": 10000, "stocksHeld": [{"name": "ADBE", "amount": 0, "value": 0.0}, {"name": "MSFT", "amount": 0, "value": 0.0}, {"name": "AVGO", "amount": 0, "value": 0.0}, {"name": "AMZN", "amount": 0, "value": 0.0}], "date": "2015-03-11"}, {"funds": 10000, "stocksHeld": [{"name": "ADBE", "amount": 0, "value": 0.0}, {"name": "MSFT", "amount": 0, "value": 0.0}, {"name": "AVGO", "amount": 0, "value": 0.0}, {"name": "AMZN", "amount": 0, "value": 0.0}], "date": "2015-03-11"}, {"funds": 10000, "stocksHeld": [{"name": "ADBE", "amount": 0, "value": 0.0}, {"name": "MSFT", "amount": 0, "value": 0.0}, {"name": "AVGO", "amount": 0, "value": 0.0}, {"name": "AMZN", "amount": 0, "value": 0.0}], "date": "2015-03-12"}, {"funds": 10000, "stocksHeld": [{"name": "ADBE", "amount": 0, "value": 0.0}, {"name": "MSFT", "amount": 0, "value": 0.0}, {"name": "AVGO", "amount": 0, "value": 0.0}, {"name": "AMZN", "amount": 0, "value": 0.0}], "date": "2015-03-12"}, {"funds": 9902.131172180176, "stocksHeld": [{"name": "ADBE", "amount": 0, "value": 0.0}, {"name": "MSFT", "amount": 0, "value": 0.0}, {"name": "AVGO", "amount": 1, "value": 97.86882781982422}, {"name": "AMZN", "amount": 0, "value": 0.0}], "date": "2015-03-12"}, {"funds": 9902.131172180176, "stocksHeld": [{"name": "ADBE", "amount": 0, "value": 0.0}, {"name": "MSFT", "amount": 0, "value": 0.0}, {"name": "AVGO", "amount": 1, "value": 97.86882781982422}, {"name": "AMZN", "amount": 0, "value": 0.0}], "date": "2015-03-12"}, {"funds": 9902.131172180176, "stocksHeld": [{"name": "ADBE", "amount": 0, "value": 0.0}, {"name": "MSFT", "amount": 0, "value": 0.0}, {"name": "AVGO", "amount": 1, "value": 96.99968719482422}, {"name": "AMZN", "amount": 0, "value": 0.0}], "date": "2015-03-13"}, {"funds": 9902.131172180176, "stocksHeld": [{"name": "ADBE", "amount": 0, "value": 0.0}, {"name": "MSFT", "amount": 0, "value": 0.0}, {"name": "AVGO", "amount": 1, "value": 96.99968719482422}, {"name": "AMZN", "amount": 0, "value": 0.0}], "date": "2015-03-13"}, {"funds": 9902.131172180176, "stocksHeld": [{"name": "ADBE", "amount": 0, "value": 0.0}, {"name": "MSFT", "amount": 0, "value": 0.0}, {"name": "AVGO", "amount": 1, "value": 96.99968719482422}, {"name": "AMZN", "amount": 0, "value": 0.0}], "date": "2015-03-13"}, {"funds": 9902.131172180176, "stocksHeld": [{"name": "ADBE", "amount": 0, "value": 0.0}, {"name": "MSFT", "amount": 0, "value": 0.0}, {"name": "AVGO", "amount": 1, "value": 96.99968719482422}, {"name": "AMZN", "amount": 0, "value": 0.0}], "date": "2015-03-13"}, {"funds": 9902.131172180176, "stocksHeld": [{"name": "ADBE", "amount": 0, "value": 0.0}, {"name": "MSFT", "amount": 0, "value": 0.0}, {"name": "AVGO", "amount": 1, "value": 100.77881622314453}, {"name": "AMZN", "amount": 0, "value": 0.0}], "date": "2015-03-16"}, {"funds": 9902.131172180176, "stocksHeld": [{"name": "ADBE", "amount": 0, "value": 0.0}, {"name": "MSFT", "amount": 0, "value": 0.0}, {"name": "AVGO", "amount": 1, "value": 100.77881622314453}, {"name": "AMZN", "amount": 0, "value": 0.0}], "date": "2015-03-16"}, {"funds": 9902.131172180176, "stocksHeld": [{"name": "ADBE", "amount": 0, "value": 0.0}, {"name": "MSFT", "amount": 0, "value": 0.0}, {"name": "AVGO", "amount": 1, "value": 100.77881622314453}, {"name": "AMZN", "amount": 0, "value": 0.0}], "date": "2015-03-16"}, {"funds": 9902.131172180176, "stocksHeld": [{"name": "ADBE", "amount": 0, "value": 0.0}, {"name": "MSFT", "amount": 0, "value": 0.0}, {"name": "AVGO", "amount": 1, "value": 100.77881622314453}, {"name": "AMZN", "amount": 0, "value": 0.0}], "date": "2015-03-16"}, {"funds": 9902.131172180176, "stocksHeld": [{"name": "ADBE", "amount": 0, "value": 0.0}, {"name": "MSFT", "amount": 0, "value": 0.0}, {"name": "AVGO", "amount": 1, "value": 100.1812973022461}, {"name": "AMZN", "amount": 0, "value": 0.0}], "date": "2015-03-17"}, {"funds": 9902.131172180176, "stocksHeld": [{"name": "ADBE", "amount": 0, "value": 0.0}, {"name": "MSFT", "amount": 0, "value": 0.0}, {"name": "AVGO", "amount": 1, "value": 100.1812973022461}, {"name": "AMZN", "amount": 0, "value": 0.0}], "date": "2015-03-17"}, {"funds": 9902.131172180176, "stocksHeld": [{"name": "ADBE", "amount": 0, "value": 0.0}, {"name": "MSFT", "amount": 0, "value": 0.0}, {"name": "AVGO", "amount": 1, "value": 100.1812973022461}, {"name": "AMZN", "amount": 0, "value": 0.0}], "date": "2015-03-17"}, {"funds": 9902.131172180176, "stocksHeld": [{"name": "ADBE", "amount": 0, "value": 0.0}, {"name": "MSFT", "amount": 0, "value": 0.0}, {"name": "AVGO", "amount": 1, "value": 100.1812973022461}, {"name": "AMZN", "amount": 0, "value": 0.0}], "date": "2015-03-17"}, {"funds": 9902.131172180176, "stocksHeld": [{"name": "ADBE", "amount": 0, "value": 0.0}, {"name": "MSFT", "amount": 0, "value": 0.0}, {"name": "AVGO", "amount": 1, "value": 101.51995849609375}, {"name": "AMZN", "amount": 0, "value": 0.0}], "date": "2015-03-18"}, {"funds": 9902.131172180176, "stocksHeld": [{"name": "ADBE", "amount": 0, "value": 0.0}, {"name": "MSFT", "amount": 0, "value": 0.0}, {"name": "AVGO", "amount": 1, "value": 101.51995849609375}, {"name": "AMZN", "amount": 0, "value": 0.0}], "date": "2015-03-18"}, {"funds": 9902.131172180176, "stocksHeld": [{"name": "ADBE", "amount": 0, "value": 0.0}, {"name": "MSFT", "amount": 0, "value": 0.0}, {"name": "AVGO", "amount": 1, "value": 101.51995849609375}, {"name": "AMZN", "amount": 0, "value": 0.0}], "date": "2015-03-18"}, {"funds": 9902.131172180176, "stocksHeld": [{"name": "ADBE", "amount": 0, "value": 0.0}, {"name": "MSFT", "amount": 0, "value": 0.0}, {"name": "AVGO", "amount": 1, "value": 101.51995849609375}, {"name": "AMZN", "amount": 0, "value": 0.0}], "date": "2015-03-18"}, {"funds": 9902.131172180176, "stocksHeld": [{"name": "ADBE", "amount": 0, "value": 0.0}, {"name": "MSFT", "amount": 0, "value": 0.0}, {"name": "AVGO", "amount": 1, "value": 102.76521301269531}, {"name": "AMZN", "amount": 0, "value": 0.0}], "date": "2015-03-19"}, {"funds": 9902.131172180176, "stocksHeld": [{"name": "ADBE", "amount": 0, "value": 0.0}, {"name": "MSFT", "amount": 0, "value": 0.0}, {"name": "AVGO", "amount": 1, "value": 102.76521301269531}, {"name": "AMZN", "amount": 0, "value": 0.0}], "date": "2015-03-19"}, {"funds": 9902.131172180176, "stocksHeld": [{"name": "ADBE", "amount": 0, "value": 0.0}, {"name": "MSFT", "amount": 0, "value": 0.0}, {"name": "AVGO", "amount": 1, "value": 102.76521301269531}, {"name": "AMZN", "amount": 0, "value": 0.0}], "date": "2015-03-19"}, {"funds": 9902.131172180176, "stocksHeld": [{"name": "ADBE", "amount": 0, "value": 0.0}, {"name": "MSFT", "amount": 0, "value": 0.0}, {"name": "AVGO", "amount": 1, "value": 102.76521301269531}, {"name": "AMZN", "amount": 0, "value": 0.0}], "date": "2015-03-19"}, {"funds": 9902.131172180176, "stocksHeld": [{"name": "ADBE", "amount": 0, "value": 0.0}, {"name": "MSFT", "amount": 0, "value": 0.0}, {"name": "AVGO", "amount": 1, "value": 103.73806762695312}, {"name": "AMZN", "amount": 0, "value": 0.0}], "date": "2015-03-20"}, {"funds": 9902.131172180176, "stocksHeld": [{"name": "ADBE", "amount": 0, "value": 0.0}, {"name": "MSFT", "amount": 0, "value": 0.0}, {"name": "AVGO", "amount": 1, "value": 103.73806762695312}, {"name": "AMZN", "amount": 0, "value": 0.0}], "date": "2015-03-20"}, {"funds": 10005.869239807129, "stocksHeld": [{"name": "ADBE", "amount": 0, "value": 0.0}, {"name": "MSFT", "amount": 0, "value": 0.0}, {"name": "AVGO", "amount": 0, "value": 0.0}, {"name": "AMZN", "amount": 0, "value": 0.0}], "date": "2015-03-20"}, {"funds": 10005.869239807129, "stocksHeld": [{"name": "ADBE", "amount": 0, "value": 0.0}, {"name": "MSFT", "amount": 0, "value": 0.0}, {"name": "AVGO", "amount": 0, "value": 0.0}, {"name": "AMZN", "amount": 0, "value": 0.0}], "date": "2015-03-20"}, {"funds": 10005.869239807129, "stocksHeld": [{"name": "ADBE", "amount": 0, "value": 0.0}, {"name": "MSFT", "amount": 0, "value": 0.0}, {"name": "AVGO", "amount": 0, "value": 0.0}, {"name": "AMZN", "amount": 0, "value": 0.0}], "date": "2015-03-23"}, {"funds": 10005.869239807129, "stocksHeld": [{"name": "ADBE", "amount": 0, "value": 0.0}, {"name": "MSFT", "amount": 0, "value": 0.0}, {"name": "AVGO", "amount": 0, "value": 0.0}, {"name": "AMZN", "amount": 0, "value": 0.0}], "date": "2015-03-23"}, {"funds": 10005.869239807129, "stocksHeld": [{"name": "ADBE", "amount": 0, "value": 0.0}, {"name": "MSFT", "amount": 0, "value": 0.0}, {"name": "AVGO", "amount": 0, "value": 0.0}, {"name": "AMZN", "amount": 0, "value": 0.0}], "date": "2015-03-23"}, {"funds": 10005.869239807129, "stocksHeld": [{"name": "ADBE", "amount": 0, "value": 0.0}, {"name": "MSFT", "amount": 0, "value": 0.0}, {"name": "AVGO", "amount": 0, "value": 0.0}, {"name": "AMZN", "amount": 0, "value": 0.0}], "date": "2015-03-23"}, {"funds": 10005.869239807129, "stocksHeld": [{"name": "ADBE", "amount": 0, "value": 0.0}, {"name": "MSFT", "amount": 0, "value": 0.0}, {"name": "AVGO", "amount": 0, "value": 0.0}, {"name": "AMZN", "amount": 0, "value": 0.0}], "date": "2015-03-24"}, {"funds": 10005.869239807129, "stocksHeld": [{"name": "ADBE", "amount": 0, "value": 0.0}, {"name": "MSFT", "amount": 0, "value": 0.0}, {"name": "AVGO", "amount": 0, "value": 0.0}, {"name": "AMZN", "amount": 0, "value": 0.0}], "date": "2015-03-24"}, {"funds": 10005.869239807129, "stocksHeld": [{"name": "ADBE", "amount": 0, "value": 0.0}, {"name": "MSFT", "amount": 0, "value": 0.0}, {"name": "AVGO", "amount": 0, "value": 0.0}, {"name": "AMZN", "amount": 0, "value": 0.0}], "date": "2015-03-24"}, {"funds": 10005.869239807129, "stocksHeld": [{"name": "ADBE", "amount": 0, "value": 0.0}, {"name": "MSFT", "amount": 0, "value": 0.0}, {"name": "AVGO", "amount": 0, "value": 0.0}, {"name": "AMZN", "amount": 0, "value": 0.0}], "date": "2015-03-24"}, {"funds": 10005.869239807129, "stocksHeld": [{"name": "ADBE", "amount": 0, "value": 0.0}, {"name": "MSFT", "amount": 0, "value": 0.0}, {"name": "AVGO", "amount": 0, "value": 0.0}, {"name": "AMZN", "amount": 0, "value": 0.0}], "date": "2015-03-25"}, {"funds": 10005.869239807129, "stocksHeld": [{"name": "ADBE", "amount": 0, "value": 0.0}, {"name": "MSFT", "amount": 0, "value": 0.0}, {"name": "AVGO", "amount": 0, "value": 0.0}, {"name": "AMZN", "amount": 0, "value": 0.0}], "date": "2015-03-25"}, {"funds": 9909.026794433594, "stocksHeld": [{"name": "ADBE", "amount": 0, "value": 0.0}, {"name": "MSFT", "amount": 0, "value": 0.0}, {"name": "AVGO", "amount": 1, "value": 96.84244537353516}, {"name": "AMZN", "amount": 0, "value": 0.0}], "date": "2015-03-25"}, {"funds": 9909.026794433594, "stocksHeld": [{"name": "ADBE", "amount": 0, "value": 0.0}, {"name": "MSFT", "amount": 0, "value": 0.0}, {"name": "AVGO", "amount": 1, "value": 96.84244537353516}, {"name": "AMZN", "amount": 0, "value": 0.0}], "date": "2015-03-25"}, {"funds": 9909.026794433594, "stocksHeld": [{"name": "ADBE", "amount": 0, "value": 0.0}, {"name": "MSFT", "amount": 0, "value": 0.0}, {"name": "AVGO", "amount": 1, "value": 97.06036376953125}, {"name": "AMZN", "amount": 0, "value": 0.0}], "date": "2015-03-26"}, {"funds": 9873.048835754395, "stocksHeld": [{"name": "ADBE", "amount": 0, "value": 0.0}, {"name": "MSFT", "amount": 1, "value": 35.97795867919922}, {"name": "AVGO", "amount": 1, "value": 97.06036376953125}, {"name": "AMZN", "amount": 0, "value": 0.0}], "date": "2015-03-26"}, {"funds": 9873.048835754395, "stocksHeld": [{"name": "ADBE", "amount": 0, "value": 0.0}, {"name": "MSFT", "amount": 1, "value": 35.97795867919922}, {"name": "AVGO", "amount": 1, "value": 97.06036376953125}, {"name": "AMZN", "amount": 0, "value": 0.0}], "date": "2015-03-26"}, {"funds": 9873.048835754395, "stocksHeld": [{"name": "ADBE", "amount": 0, "value": 0.0}, {"name": "MSFT", "amount": 1, "value": 35.97795867919922}, {"name": "AVGO", "amount": 1, "value": 97.06036376953125}, {"name": "AMZN", "amount": 0, "value": 0.0}], "date": "2015-03-26"}, {"funds": 9873.048835754395, "stocksHeld": [{"name": "ADBE", "amount": 0, "value": 0.0}, {"name": "MSFT", "amount": 1, "value": 35.7684326171875}, {"name": "AVGO", "amount": 1, "value": 99.78437805175781}, {"name": "AMZN", "amount": 0, "value": 0.0}], "date": "2015-03-27"}, {"funds": 9873.048835754395, "stocksHeld": [{"name": "ADBE", "amount": 0, "value": 0.0}, {"name": "MSFT", "amount": 1, "value": 35.7684326171875}, {"name": "AVGO", "amount": 1, "value": 99.78437805175781}, {"name": "AMZN", "amount": 0, "value": 0.0}], "date": "2015-03-27"}, {"funds": 9873.048835754395, "stocksHeld": [{"name": "ADBE", "amount": 0, "value": 0.0}, {"name": "MSFT", "amount": 1, "value": 35.7684326171875}, {"name": "AVGO", "amount": 1, "value": 99.78437805175781}, {"name": "AMZN", "amount": 0, "value": 0.0}], "date": "2015-03-27"}, {"funds": 9873.048835754395, "stocksHeld": [{"name": "ADBE", "amount": 0, "value": 0.0}, {"name": "MSFT", "amount": 1, "value": 35.7684326171875}, {"name": "AVGO", "amount": 1, "value": 99.78437805175781}, {"name": "AMZN", "amount": 0, "value": 0.0}], "date": "2015-03-27"}, {"funds": 9873.048835754395, "stocksHeld": [{"name": "ADBE", "amount": 0, "value": 0.0}, {"name": "MSFT", "amount": 1, "value": 35.75968551635742}, {"name": "AVGO", "amount": 1, "value": 101.60556030273438}, {"name": "AMZN", "amount": 0, "value": 0.0}], "date": "2015-03-30"}, {"funds": 9873.048835754395, "stocksHeld": [{"name": "ADBE", "amount": 0, "value": 0.0}, {"name": "MSFT", "amount": 1, "value": 35.75968551635742}, {"name": "AVGO", "amount": 1, "value": 101.60556030273438}, {"name": "AMZN", "amount": 0, "value": 0.0}], "date": "2015-03-30"}, {"funds": 9873.048835754395, "stocksHeld": [{"name": "ADBE", "amount": 0, "value": 0.0}, {"name": "MSFT", "amount": 1, "value": 35.75968551635742}, {"name": "AVGO", "amount": 1, "value": 101.60556030273438}, {"name": "AMZN", "amount": 0, "value": 0.0}], "date": "2015-03-30"}, {"funds": 9873.048835754395, "stocksHeld": [{"name": "ADBE", "amount": 0, "value": 0.0}, {"name": "MSFT", "amount": 1, "value": 35.75968551635742}, {"name": "AVGO", "amount": 1, "value": 101.60556030273438}, {"name": "AMZN", "amount": 0, "value": 0.0}], "date": "2015-03-30"}, {"funds": 9873.048835754395, "stocksHeld": [{"name": "ADBE", "amount": 0, "value": 0.0}, {"name": "MSFT", "amount": 1, "value": 35.497779846191406}, {"name": "AVGO", "amount": 1, "value": 98.82707214355469}, {"name": "AMZN", "amount": 0, "value": 0.0}], "date": "2015-03-31"}, {"funds": 9873.048835754395, "stocksHeld": [{"name": "ADBE", "amount": 0, "value": 0.0}, {"name": "MSFT", "amount": 1, "value": 35.497779846191406}, {"name": "AVGO", "amount": 1, "value": 98.82707214355469}, {"name": "AMZN", "amount": 0, "value": 0.0}], "date": "2015-03-31"}, {"funds": 9873.048835754395, "stocksHeld": [{"name": "ADBE", "amount": 0, "value": 0.0}, {"name": "MSFT", "amount": 1, "value": 35.497779846191406}, {"name": "AVGO", "amount": 1, "value": 98.82707214355469}, {"name": "AMZN", "amount": 0, "value": 0.0}], "date": "2015-03-31"}, {"funds": 9873.048835754395, "stocksHeld": [{"name": "ADBE", "amount": 0, "value": 0.0}, {"name": "MSFT", "amount": 1, "value": 35.497779846191406}, {"name": "AVGO", "amount": 1, "value": 98.82707214355469}, {"name": "AMZN", "amount": 0, "value": 0.0}], "date": "2015-03-31"}, {"funds": 9873.048835754395, "stocksHeld": [{"name": "ADBE", "amount": 0, "value": 0.0}, {"name": "MSFT", "amount": 1, "value": 35.55015182495117}, {"name": "AVGO", "amount": 1, "value": 97.77641296386719}, {"name": "AMZN", "amount": 0, "value": 0.0}], "date": "2015-04-01"}, {"funds": 9873.048835754395, "stocksHeld": [{"name": "ADBE", "amount": 0, "value": 0.0}, {"name": "MSFT", "amount": 1, "value": 35.55015182495117}, {"name": "AVGO", "amount": 1, "value": 97.77641296386719}, {"name": "AMZN", "amount": 0, "value": 0.0}], "date": "2015-04-01"}, {"funds": 9873.048835754395, "stocksHeld": [{"name": "ADBE", "amount": 0, "value": 0.0}, {"name": "MSFT", "amount": 1, "value": 35.55015182495117}, {"name": "AVGO", "amount": 1, "value": 97.77641296386719}, {"name": "AMZN", "amount": 0, "value": 0.0}], "date": "2015-04-01"}, {"funds": 9873.048835754395, "stocksHeld": [{"name": "ADBE", "amount": 0, "value": 0.0}, {"name": "MSFT", "amount": 1, "value": 35.55015182495117}, {"name": "AVGO", "amount": 1, "value": 97.77641296386719}, {"name": "AMZN", "amount": 0, "value": 0.0}], "date": "2015-04-01"}, {"funds": 9873.048835754395, "stocksHeld": [{"name": "ADBE", "amount": 0, "value": 0.0}, {"name": "MSFT", "amount": 1, "value": 35.174747467041016}, {"name": "AVGO", "amount": 1, "value": 97.30164337158203}, {"name": "AMZN", "amount": 0, "value": 0.0}], "date": "2015-04-02"}, {"funds": 9873.048835754395, "stocksHeld": [{"name": "ADBE", "amount": 0, "value": 0.0}, {"name": "MSFT", "amount": 1, "value": 35.174747467041016}, {"name": "AVGO", "amount": 1, "value": 97.30164337158203}, {"name": "AMZN", "amount": 0, "value": 0.0}], "date": "2015-04-02"}, {"funds": 9873.048835754395, "stocksHeld": [{"name": "ADBE", "amount": 0, "value": 0.0}, {"name": "MSFT", "amount": 1, "value": 35.174747467041016}, {"name": "AVGO", "amount": 1, "value": 97.30164337158203}, {"name": "AMZN", "amount": 0, "value": 0.0}], "date": "2015-04-02"}, {"funds": 9873.048835754395, "stocksHeld": [{"name": "ADBE", "amount": 0, "value": 0.0}, {"name": "MSFT", "amount": 1, "value": 35.174747467041016}, {"name": "AVGO", "amount": 1, "value": 97.30164337158203}, {"name": "AMZN", "amount": 0, "value": 0.0}], "date": "2015-04-02"}, {"funds": 9873.048835754395, "stocksHeld": [{"name": "ADBE", "amount": 0, "value": 0.0}, {"name": "MSFT", "amount": 1, "value": 36.274776458740234}, {"name": "AVGO", "amount": 1, "value": 97.93203735351562}, {"name": "AMZN", "amount": 0, "value": 0.0}], "date": "2015-04-06"}, {"funds": 9873.048835754395, "stocksHeld": [{"name": "ADBE", "amount": 0, "value": 0.0}, {"name": "MSFT", "amount": 1, "value": 36.274776458740234}, {"name": "AVGO", "amount": 1, "value": 97.93203735351562}, {"name": "AMZN", "amount": 0, "value": 0.0}], "date": "2015-04-06"}, {"funds": 9873.048835754395, "stocksHeld": [{"name": "ADBE", "amount": 0, "value": 0.0}, {"name": "MSFT", "amount": 1, "value": 36.274776458740234}, {"name": "AVGO", "amount": 1, "value": 97.93203735351562}, {"name": "AMZN", "amount": 0, "value": 0.0}], "date": "2015-04-06"}, {"funds": 9873.048835754395, "stocksHeld": [{"name": "ADBE", "amount": 0, "value": 0.0}, {"name": "MSFT", "amount": 1, "value": 36.274776458740234}, {"name": "AVGO", "amount": 1, "value": 97.93203735351562}, {"name": "AMZN", "amount": 0, "value": 0.0}], "date": "2015-04-06"}, {"funds": 9873.048835754395, "stocksHeld": [{"name": "ADBE", "amount": 0, "value": 0.0}, {"name": "MSFT", "amount": 1, "value": 36.25732421875}, {"name": "AVGO", "amount": 1, "value": 97.79193878173828}, {"name": "AMZN", "amount": 0, "value": 0.0}], "date": "2015-04-07"}, {"funds": 9909.306159973145, "stocksHeld": [{"name": "ADBE", "amount": 0, "value": 0.0}, {"name": "MSFT", "amount": 0, "value": 0.0}, {"name": "AVGO", "amount": 1, "value": 97.79193878173828}, {"name": "AMZN", "amount": 0, "value": 0.0}], "date": "2015-04-07"}, {"funds": 9909.306159973145, "stocksHeld": [{"name": "ADBE", "amount": 0, "value": 0.0}, {"name": "MSFT", "amount": 0, "value": 0.0}, {"name": "AVGO", "amount": 1, "value": 97.79193878173828}, {"name": "AMZN", "amount": 0, "value": 0.0}], "date": "2015-04-07"}, {"funds": 9909.306159973145, "stocksHeld": [{"name": "ADBE", "amount": 0, "value": 0.0}, {"name": "MSFT", "amount": 0, "value": 0.0}, {"name": "AVGO", "amount": 1, "value": 97.79193878173828}, {"name": "AMZN", "amount": 0, "value": 0.0}], "date": "2015-04-07"}, {"funds": 9909.306159973145, "stocksHeld": [{"name": "ADBE", "amount": 0, "value": 0.0}, {"name": "MSFT", "amount": 0, "value": 0.0}, {"name": "AVGO", "amount": 1, "value": 98.67919921875}, {"name": "AMZN", "amount": 0, "value": 0.0}], "date": "2015-04-08"}, {"funds": 9909.306159973145, "stocksHeld": [{"name": "ADBE", "amount": 0, "value": 0.0}, {"name": "MSFT", "amount": 0, "value": 0.0}, {"name": "AVGO", "amount": 1, "value": 98.67919921875}, {"name": "AMZN", "amount": 0, "value": 0.0}], "date": "2015-04-08"}, {"funds": 9909.306159973145, "stocksHeld": [{"name": "ADBE", "amount": 0, "value": 0.0}, {"name": "MSFT", "amount": 0, "value": 0.0}, {"name": "AVGO", "amount": 1, "value": 98.67919921875}, {"name": "AMZN", "amount": 0, "value": 0.0}], "date": "2015-04-08"}, {"funds": 9909.306159973145, "stocksHeld": [{"name": "ADBE", "amount": 0, "value": 0.0}, {"name": "MSFT", "amount": 0, "value": 0.0}, {"name": "AVGO", "amount": 1, "value": 98.67919921875}, {"name": "AMZN", "amount": 0, "value": 0.0}], "date": "2015-04-08"}, {"funds": 9909.306159973145, "stocksHeld": [{"name": "ADBE", "amount": 0, "value": 0.0}, {"name": "MSFT", "amount": 0, "value": 0.0}, {"name": "AVGO", "amount": 1, "value": 99.01388549804688}, {"name": "AMZN", "amount": 0, "value": 0.0}], "date": "2015-04-09"}, {"funds": 9909.306159973145, "stocksHeld": [{"name": "ADBE", "amount": 0, "value": 0.0}, {"name": "MSFT", "amount": 0, "value": 0.0}, {"name": "AVGO", "amount": 1, "value": 99.01388549804688}, {"name": "AMZN", "amount": 0, "value": 0.0}], "date": "2015-04-09"}, {"funds": 9909.306159973145, "stocksHeld": [{"name": "ADBE", "amount": 0, "value": 0.0}, {"name": "MSFT", "amount": 0, "value": 0.0}, {"name": "AVGO", "amount": 1, "value": 99.01388549804688}, {"name": "AMZN", "amount": 0, "value": 0.0}], "date": "2015-04-09"}, {"funds": 9909.306159973145, "stocksHeld": [{"name": "ADBE", "amount": 0, "value": 0.0}, {"name": "MSFT", "amount": 0, "value": 0.0}, {"name": "AVGO", "amount": 1, "value": 99.01388549804688}, {"name": "AMZN", "amount": 0, "value": 0.0}], "date": "2015-04-09"}, {"funds": 9909.306159973145, "stocksHeld": [{"name": "ADBE", "amount": 0, "value": 0.0}, {"name": "MSFT", "amount": 0, "value": 0.0}, {"name": "AVGO", "amount": 1, "value": 98.70255279541016}, {"name": "AMZN", "amount": 0, "value": 0.0}], "date": "2015-04-10"}, {"funds": 9909.306159973145, "stocksHeld": [{"name": "ADBE", "amount": 0, "value": 0.0}, {"name": "MSFT", "amount": 0, "value": 0.0}, {"name": "AVGO", "amount": 1, "value": 98.70255279541016}, {"name": "AMZN", "amount": 0, "value": 0.0}], "date": "2015-04-10"}, {"funds": 9909.306159973145, "stocksHeld": [{"name": "ADBE", "amount": 0, "value": 0.0}, {"name": "MSFT", "amount": 0, "value": 0.0}, {"name": "AVGO", "amount": 1, "value": 98.70255279541016}, {"name": "AMZN", "amount": 0, "value": 0.0}], "date": "2015-04-10"}, {"funds": 9909.306159973145, "stocksHeld": [{"name": "ADBE", "amount": 0, "value": 0.0}, {"name": "MSFT", "amount": 0, "value": 0.0}, {"name": "AVGO", "amount": 1, "value": 98.70255279541016}, {"name": "AMZN", "amount": 0, "value": 0.0}], "date": "2015-04-10"}, {"funds": 9909.306159973145, "stocksHeld": [{"name": "ADBE", "amount": 0, "value": 0.0}, {"name": "MSFT", "amount": 0, "value": 0.0}, {"name": "AVGO", "amount": 1, "value": 97.55846405029297}, {"name": "AMZN", "amount": 0, "value": 0.0}], "date": "2015-04-13"}, {"funds": 9909.306159973145, "stocksHeld": [{"name": "ADBE", "amount": 0, "value": 0.0}, {"name": "MSFT", "amount": 0, "value": 0.0}, {"name": "AVGO", "amount": 1, "value": 97.55846405029297}, {"name": "AMZN", "amount": 0, "value": 0.0}], "date": "2015-04-13"}, {"funds": 9909.306159973145, "stocksHeld": [{"name": "ADBE", "amount": 0, "value": 0.0}, {"name": "MSFT", "amount": 0, "value": 0.0}, {"name": "AVGO", "amount": 1, "value": 97.55846405029297}, {"name": "AMZN", "amount": 0, "value": 0.0}], "date": "2015-04-13"}, {"funds": 9909.306159973145, "stocksHeld": [{"name": "ADBE", "amount": 0, "value": 0.0}, {"name": "MSFT", "amount": 0, "value": 0.0}, {"name": "AVGO", "amount": 1, "value": 97.55846405029297}, {"name": "AMZN", "amount": 0, "value": 0.0}], "date": "2015-04-13"}, {"funds": 9909.306159973145, "stocksHeld": [{"name": "ADBE", "amount": 0, "value": 0.0}, {"name": "MSFT", "amount": 0, "value": 0.0}, {"name": "AVGO", "amount": 1, "value": 96.49219512939453}, {"name": "AMZN", "amount": 0, "value": 0.0}], "date": "2015-04-14"}, {"funds": 9909.306159973145, "stocksHeld": [{"name": "ADBE", "amount": 0, "value": 0.0}, {"name": "MSFT", "amount": 0, "value": 0.0}, {"name": "AVGO", "amount": 1, "value": 96.49219512939453}, {"name": "AMZN", "amount": 0, "value": 0.0}], "date": "2015-04-14"}, {"funds": 9909.306159973145, "stocksHeld": [{"name": "ADBE", "amount": 0, "value": 0.0}, {"name": "MSFT", "amount": 0, "value": 0.0}, {"name": "AVGO", "amount": 1, "value": 96.49219512939453}, {"name": "AMZN", "amount": 0, "value": 0.0}], "date": "2015-04-14"}, {"funds": 9909.306159973145, "stocksHeld": [{"name": "ADBE", "amount": 0, "value": 0.0}, {"name": "MSFT", "amount": 0, "value": 0.0}, {"name": "AVGO", "amount": 1, "value": 96.49219512939453}, {"name": "AMZN", "amount": 0, "value": 0.0}], "date": "2015-04-14"}, {"funds": 9909.306159973145, "stocksHeld": [{"name": "ADBE", "amount": 0, "value": 0.0}, {"name": "MSFT", "amount": 0, "value": 0.0}, {"name": "AVGO", "amount": 1, "value": 97.98651123046875}, {"name": "AMZN", "amount": 0, "value": 0.0}], "date": "2015-04-15"}, {"funds": 9909.306159973145, "stocksHeld": [{"name": "ADBE", "amount": 0, "value": 0.0}, {"name": "MSFT", "amount": 0, "value": 0.0}, {"name": "AVGO", "amount": 1, "value": 97.98651123046875}, {"name": "AMZN", "amount": 0, "value": 0.0}], "date": "2015-04-15"}, {"funds": 9909.306159973145, "stocksHeld": [{"name": "ADBE", "amount": 0, "value": 0.0}, {"name": "MSFT", "amount": 0, "value": 0.0}, {"name": "AVGO", "amount": 1, "value": 97.98651123046875}, {"name": "AMZN", "amount": 0, "value": 0.0}], "date": "2015-04-15"}, {"funds": 9909.306159973145, "stocksHeld": [{"name": "ADBE", "amount": 0, "value": 0.0}, {"name": "MSFT", "amount": 0, "value": 0.0}, {"name": "AVGO", "amount": 1, "value": 97.98651123046875}, {"name": "AMZN", "amount": 0, "value": 0.0}], "date": "2015-04-15"}, {"funds": 9909.306159973145, "stocksHeld": [{"name": "ADBE", "amount": 0, "value": 0.0}, {"name": "MSFT", "amount": 0, "value": 0.0}, {"name": "AVGO", "amount": 1, "value": 97.54292297363281}, {"name": "AMZN", "amount": 0, "value": 0.0}], "date": "2015-04-16"}, {"funds": 9909.306159973145, "stocksHeld": [{"name": "ADBE", "amount": 0, "value": 0.0}, {"name": "MSFT", "amount": 0, "value": 0.0}, {"name": "AVGO", "amount": 1, "value": 97.54292297363281}, {"name": "AMZN", "amount": 0, "value": 0.0}], "date": "2015-04-16"}, {"funds": 9909.306159973145, "stocksHeld": [{"name": "ADBE", "amount": 0, "value": 0.0}, {"name": "MSFT", "amount": 0, "value": 0.0}, {"name": "AVGO", "amount": 1, "value": 97.54292297363281}, {"name": "AMZN", "amount": 0, "value": 0.0}], "date": "2015-04-16"}, {"funds": 9909.306159973145, "stocksHeld": [{"name": "ADBE", "amount": 0, "value": 0.0}, {"name": "MSFT", "amount": 0, "value": 0.0}, {"name": "AVGO", "amount": 1, "value": 97.54292297363281}, {"name": "AMZN", "amount": 0, "value": 0.0}], "date": "2015-04-16"}, {"funds": 9836.156158447266, "stocksHeld": [{"name": "ADBE", "amount": 1, "value": 73.1500015258789}, {"name": "MSFT", "amount": 0, "value": 0.0}, {"name": "AVGO", "amount": 1, "value": 94.8344497680664}, {"name": "AMZN", "amount": 0, "value": 0.0}], "date": "2015-04-17"}, {"funds": 9836.156158447266, "stocksHeld": [{"name": "ADBE", "amount": 1, "value": 73.1500015258789}, {"name": "MSFT", "amount": 0, "value": 0.0}, {"name": "AVGO", "amount": 1, "value": 94.8344497680664}, {"name": "AMZN", "amount": 0, "value": 0.0}], "date": "2015-04-17"}, {"funds": 9836.156158447266, "stocksHeld": [{"name": "ADBE", "amount": 1, "value": 73.1500015258789}, {"name": "MSFT", "amount": 0, "value": 0.0}, {"name": "AVGO", "amount": 1, "value": 94.8344497680664}, {"name": "AMZN", "amount": 0, "value": 0.0}], "date": "2015-04-17"}, {"funds": 9836.156158447266, "stocksHeld": [{"name": "ADBE", "amount": 1, "value": 73.1500015258789}, {"name": "MSFT", "amount": 0, "value": 0.0}, {"name": "AVGO", "amount": 1, "value": 94.8344497680664}, {"name": "AMZN", "amount": 0, "value": 0.0}], "date": "2015-04-17"}, {"funds": 9836.156158447266, "stocksHeld": [{"name": "ADBE", "amount": 1, "value": 73.91999816894531}, {"name": "MSFT", "amount": 0, "value": 0.0}, {"name": "AVGO", "amount": 1, "value": 95.75283813476562}, {"name": "AMZN", "amount": 0, "value": 0.0}], "date": "2015-04-20"}, {"funds": 9836.156158447266, "stocksHeld": [{"name": "ADBE", "amount": 1, "value": 73.91999816894531}, {"name": "MSFT", "amount": 0, "value": 0.0}, {"name": "AVGO", "amount": 1, "value": 95.75283813476562}, {"name": "AMZN", "amount": 0, "value": 0.0}], "date": "2015-04-20"}, {"funds": 9836.156158447266, "stocksHeld": [{"name": "ADBE", "amount": 1, "value": 73.91999816894531}, {"name": "MSFT", "amount": 0, "value": 0.0}, {"name": "AVGO", "amount": 1, "value": 95.75283813476562}, {"name": "AMZN", "amount": 0, "value": 0.0}], "date": "2015-04-20"}, {"funds": 9836.156158447266, "stocksHeld": [{"name": "ADBE", "amount": 1, "value": 73.91999816894531}, {"name": "MSFT", "amount": 0, "value": 0.0}, {"name": "AVGO", "amount": 1, "value": 95.75283813476562}, {"name": "AMZN", "amount": 0, "value": 0.0}], "date": "2015-04-20"}, {"funds": 9836.156158447266, "stocksHeld": [{"name": "ADBE", "amount": 1, "value": 74.62000274658203}, {"name": "MSFT", "amount": 0, "value": 0.0}, {"name": "AVGO", "amount": 1, "value": 95.80730438232422}, {"name": "AMZN", "amount": 0, "value": 0.0}], "date": "2015-04-21"}, {"funds": 9836.156158447266, "stocksHeld": [{"name": "ADBE", "amount": 1, "value": 74.62000274658203}, {"name": "MSFT", "amount": 0, "value": 0.0}, {"name": "AVGO", "amount": 1, "value": 95.80730438232422}, {"name": "AMZN", "amount": 0, "value": 0.0}], "date": "2015-04-21"}, {"funds": 9836.156158447266, "stocksHeld": [{"name": "ADBE", "amount": 1, "value": 74.62000274658203}, {"name": "MSFT", "amount": 0, "value": 0.0}, {"name": "AVGO", "amount": 1, "value": 95.80730438232422}, {"name": "AMZN", "amount": 0, "value": 0.0}], "date": "2015-04-21"}, {"funds": 9836.156158447266, "stocksHeld": [{"name": "ADBE", "amount": 1, "value": 74.62000274658203}, {"name": "MSFT", "amount": 0, "value": 0.0}, {"name": "AVGO", "amount": 1, "value": 95.80730438232422}, {"name": "AMZN", "amount": 0, "value": 0.0}], "date": "2015-04-21"}, {"funds": 9836.156158447266, "stocksHeld": [{"name": "ADBE", "amount": 1, "value": 75.5}, {"name": "MSFT", "amount": 0, "value": 0.0}, {"name": "AVGO", "amount": 1, "value": 99.54310607910156}, {"name": "AMZN", "amount": 0, "value": 0.0}], "date": "2015-04-22"}, {"funds": 9836.156158447266, "stocksHeld": [{"name": "ADBE", "amount": 1, "value": 75.5}, {"name": "MSFT", "amount": 0, "value": 0.0}, {"name": "AVGO", "amount": 1, "value": 99.54310607910156}, {"name": "AMZN", "amount": 0, "value": 0.0}], "date": "2015-04-22"}, {"funds": 9836.156158447266, "stocksHeld": [{"name": "ADBE", "amount": 1, "value": 75.5}, {"name": "MSFT", "amount": 0, "value": 0.0}, {"name": "AVGO", "amount": 1, "value": 99.54310607910156}, {"name": "AMZN", "amount": 0, "value": 0.0}], "date": "2015-04-22"}, {"funds": 9836.156158447266, "stocksHeld": [{"name": "ADBE", "amount": 1, "value": 75.5}, {"name": "MSFT", "amount": 0, "value": 0.0}, {"name": "AVGO", "amount": 1, "value": 99.54310607910156}, {"name": "AMZN", "amount": 0, "value": 0.0}], "date": "2015-04-22"}, {"funds": 9912.676155090332, "stocksHeld": [{"name": "ADBE", "amount": 0, "value": 0.0}, {"name": "MSFT", "amount": 0, "value": 0.0}, {"name": "AVGO", "amount": 1, "value": 96.56226348876953}, {"name": "AMZN", "amount": 0, "value": 0.0}], "date": "2015-04-23"}, {"funds": 9912.676155090332, "stocksHeld": [{"name": "ADBE", "amount": 0, "value": 0.0}, {"name": "MSFT", "amount": 0, "value": 0.0}, {"name": "AVGO", "amount": 1, "value": 96.56226348876953}, {"name": "AMZN", "amount": 0, "value": 0.0}], "date": "2015-04-23"}, {"funds": 9912.676155090332, "stocksHeld": [{"name": "ADBE", "amount": 0, "value": 0.0}, {"name": "MSFT", "amount": 0, "value": 0.0}, {"name": "AVGO", "amount": 1, "value": 96.56226348876953}, {"name": "AMZN", "amount": 0, "value": 0.0}], "date": "2015-04-23"}, {"funds": 9912.676155090332, "stocksHeld": [{"name": "ADBE", "amount": 0, "value": 0.0}, {"name": "MSFT", "amount": 0, "value": 0.0}, {"name": "AVGO", "amount": 1, "value": 96.56226348876953}, {"name": "AMZN", "amount": 0, "value": 0.0}], "date": "2015-04-23"}, {"funds": 9912.676155090332, "stocksHeld": [{"name": "ADBE", "amount": 0, "value": 0.0}, {"name": "MSFT", "amount": 0, "value": 0.0}, {"name": "AVGO", "amount": 1, "value": 93.00547790527344}, {"name": "AMZN", "amount": 0, "value": 0.0}], "date": "2015-04-24"}, {"funds": 9912.676155090332, "stocksHeld": [{"name": "ADBE", "amount": 0, "value": 0.0}, {"name": "MSFT", "amount": 0, "value": 0.0}, {"name": "AVGO", "amount": 1, "value": 93.00547790527344}, {"name": "AMZN", "amount": 0, "value": 0.0}], "date": "2015-04-24"}, {"funds": 9912.676155090332, "stocksHeld": [{"name": "ADBE", "amount": 0, "value": 0.0}, {"name": "MSFT", "amount": 0, "value": 0.0}, {"name": "AVGO", "amount": 1, "value": 93.00547790527344}, {"name": "AMZN", "amount": 0, "value": 0.0}], "date": "2015-04-24"}, {"funds": 9912.676155090332, "stocksHeld": [{"name": "ADBE", "amount": 0, "value": 0.0}, {"name": "MSFT", "amount": 0, "value": 0.0}, {"name": "AVGO", "amount": 1, "value": 93.00547790527344}, {"name": "AMZN", "amount": 0, "value": 0.0}], "date": "2015-04-24"}, {"funds": 9912.676155090332, "stocksHeld": [{"name": "ADBE", "amount": 0, "value": 0.0}, {"name": "MSFT", "amount": 0, "value": 0.0}, {"name": "AVGO", "amount": 1, "value": 93.5113525390625}, {"name": "AMZN", "amount": 0, "value": 0.0}], "date": "2015-04-27"}, {"funds": 9912.676155090332, "stocksHeld": [{"name": "ADBE", "amount": 0, "value": 0.0}, {"name": "MSFT", "amount": 0, "value": 0.0}, {"name": "AVGO", "amount": 1, "value": 93.5113525390625}, {"name": "AMZN", "amount": 0, "value": 0.0}], "date": "2015-04-27"}, {"funds": 9912.676155090332, "stocksHeld": [{"name": "ADBE", "amount": 0, "value": 0.0}, {"name": "MSFT", "amount": 0, "value": 0.0}, {"name": "AVGO", "amount": 1, "value": 93.5113525390625}, {"name": "AMZN", "amount": 0, "value": 0.0}], "date": "2015-04-27"}, {"funds": 9912.676155090332, "stocksHeld": [{"name": "ADBE", "amount": 0, "value": 0.0}, {"name": "MSFT", "amount": 0, "value": 0.0}, {"name": "AVGO", "amount": 1, "value": 93.5113525390625}, {"name": "AMZN", "amount": 0, "value": 0.0}], "date": "2015-04-27"}, {"funds": 9912.676155090332, "stocksHeld": [{"name": "ADBE", "amount": 0, "value": 0.0}, {"name": "MSFT", "amount": 0, "value": 0.0}, {"name": "AVGO", "amount": 1, "value": 91.40996551513672}, {"name": "AMZN", "amount": 0, "value": 0.0}], "date": "2015-04-28"}, {"funds": 9912.676155090332, "stocksHeld": [{"name": "ADBE", "amount": 0, "value": 0.0}, {"name": "MSFT", "amount": 0, "value": 0.0}, {"name": "AVGO", "amount": 1, "value": 91.40996551513672}, {"name": "AMZN", "amount": 0, "value": 0.0}], "date": "2015-04-28"}, {"funds": 9912.676155090332, "stocksHeld": [{"name": "ADBE", "amount": 0, "value": 0.0}, {"name": "MSFT", "amount": 0, "value": 0.0}, {"name": "AVGO", "amount": 1, "value": 91.40996551513672}, {"name": "AMZN", "amount": 0, "value": 0.0}], "date": "2015-04-28"}, {"funds": 9912.676155090332, "stocksHeld": [{"name": "ADBE", "amount": 0, "value": 0.0}, {"name": "MSFT", "amount": 0, "value": 0.0}, {"name": "AVGO", "amount": 1, "value": 91.40996551513672}, {"name": "AMZN", "amount": 0, "value": 0.0}], "date": "2015-04-28"}, {"funds": 9912.676155090332, "stocksHeld": [{"name": "ADBE", "amount": 0, "value": 0.0}, {"name": "MSFT", "amount": 0, "value": 0.0}, {"name": "AVGO", "amount": 1, "value": 91.08309173583984}, {"name": "AMZN", "amount": 0, "value": 0.0}], "date": "2015-04-29"}, {"funds": 9912.676155090332, "stocksHeld": [{"name": "ADBE", "amount": 0, "value": 0.0}, {"name": "MSFT", "amount": 0, "value": 0.0}, {"name": "AVGO", "amount": 1, "value": 91.08309173583984}, {"name": "AMZN", "amount": 0, "value": 0.0}], "date": "2015-04-29"}, {"funds": 9912.676155090332, "stocksHeld": [{"name": "ADBE", "amount": 0, "value": 0.0}, {"name": "MSFT", "amount": 0, "value": 0.0}, {"name": "AVGO", "amount": 1, "value": 91.08309173583984}, {"name": "AMZN", "amount": 0, "value": 0.0}], "date": "2015-04-29"}, {"funds": 9912.676155090332, "stocksHeld": [{"name": "ADBE", "amount": 0, "value": 0.0}, {"name": "MSFT", "amount": 0, "value": 0.0}, {"name": "AVGO", "amount": 1, "value": 91.08309173583984}, {"name": "AMZN", "amount": 0, "value": 0.0}], "date": "2015-04-29"}, {"funds": 9912.676155090332, "stocksHeld": [{"name": "ADBE", "amount": 0, "value": 0.0}, {"name": "MSFT", "amount": 0, "value": 0.0}, {"name": "AVGO", "amount": 1, "value": 90.96635437011719}, {"name": "AMZN", "amount": 0, "value": 0.0}], "date": "2015-04-30"}, {"funds": 9912.676155090332, "stocksHeld": [{"name": "ADBE", "amount": 0, "value": 0.0}, {"name": "MSFT", "amount": 0, "value": 0.0}, {"name": "AVGO", "amount": 1, "value": 90.96635437011719}, {"name": "AMZN", "amount": 0, "value": 0.0}], "date": "2015-04-30"}, {"funds": 9912.676155090332, "stocksHeld": [{"name": "ADBE", "amount": 0, "value": 0.0}, {"name": "MSFT", "amount": 0, "value": 0.0}, {"name": "AVGO", "amount": 1, "value": 90.96635437011719}, {"name": "AMZN", "amount": 0, "value": 0.0}], "date": "2015-04-30"}, {"funds": 9912.676155090332, "stocksHeld": [{"name": "ADBE", "amount": 0, "value": 0.0}, {"name": "MSFT", "amount": 0, "value": 0.0}, {"name": "AVGO", "amount": 1, "value": 90.96635437011719}, {"name": "AMZN", "amount": 0, "value": 0.0}], "date": "2015-04-30"}, {"funds": 9912.676155090332, "stocksHeld": [{"name": "ADBE", "amount": 0, "value": 0.0}, {"name": "MSFT", "amount": 0, "value": 0.0}, {"name": "AVGO", "amount": 1, "value": 95.57384490966797}, {"name": "AMZN", "amount": 0, "value": 0.0}], "date": "2015-05-01"}, {"funds": 9912.676155090332, "stocksHeld": [{"name": "ADBE", "amount": 0, "value": 0.0}, {"name": "MSFT", "amount": 0, "value": 0.0}, {"name": "AVGO", "amount": 1, "value": 95.57384490966797}, {"name": "AMZN", "amount": 0, "value": 0.0}], "date": "2015-05-01"}, {"funds": 9912.676155090332, "stocksHeld": [{"name": "ADBE", "amount": 0, "value": 0.0}, {"name": "MSFT", "amount": 0, "value": 0.0}, {"name": "AVGO", "amount": 1, "value": 95.57384490966797}, {"name": "AMZN", "amount": 0, "value": 0.0}], "date": "2015-05-01"}, {"funds": 9912.676155090332, "stocksHeld": [{"name": "ADBE", "amount": 0, "value": 0.0}, {"name": "MSFT", "amount": 0, "value": 0.0}, {"name": "AVGO", "amount": 1, "value": 95.57384490966797}, {"name": "AMZN", "amount": 0, "value": 0.0}], "date": "2015-05-01"}, {"funds": 9912.676155090332, "stocksHeld": [{"name": "ADBE", "amount": 0, "value": 0.0}, {"name": "MSFT", "amount": 0, "value": 0.0}, {"name": "AVGO", "amount": 1, "value": 94.29744720458984}, {"name": "AMZN", "amount": 0, "value": 0.0}], "date": "2015-05-04"}, {"funds": 9912.676155090332, "stocksHeld": [{"name": "ADBE", "amount": 0, "value": 0.0}, {"name": "MSFT", "amount": 0, "value": 0.0}, {"name": "AVGO", "amount": 1, "value": 94.29744720458984}, {"name": "AMZN", "amount": 0, "value": 0.0}], "date": "2015-05-04"}, {"funds": 9912.676155090332, "stocksHeld": [{"name": "ADBE", "amount": 0, "value": 0.0}, {"name": "MSFT", "amount": 0, "value": 0.0}, {"name": "AVGO", "amount": 1, "value": 94.29744720458984}, {"name": "AMZN", "amount": 0, "value": 0.0}], "date": "2015-05-04"}, {"funds": 9912.676155090332, "stocksHeld": [{"name": "ADBE", "amount": 0, "value": 0.0}, {"name": "MSFT", "amount": 0, "value": 0.0}, {"name": "AVGO", "amount": 1, "value": 94.29744720458984}, {"name": "AMZN", "amount": 0, "value": 0.0}], "date": "2015-05-04"}, {"funds": 9912.676155090332, "stocksHeld": [{"name": "ADBE", "amount": 0, "value": 0.0}, {"name": "MSFT", "amount": 0, "value": 0.0}, {"name": "AVGO", "amount": 1, "value": 90.89632415771484}, {"name": "AMZN", "amount": 0, "value": 0.0}], "date": "2015-05-05"}, {"funds": 9912.676155090332, "stocksHeld": [{"name": "ADBE", "amount": 0, "value": 0.0}, {"name": "MSFT", "amount": 0, "value": 0.0}, {"name": "AVGO", "amount": 1, "value": 90.89632415771484}, {"name": "AMZN", "amount": 0, "value": 0.0}], "date": "2015-05-05"}, {"funds": 9912.676155090332, "stocksHeld": [{"name": "ADBE", "amount": 0, "value": 0.0}, {"name": "MSFT", "amount": 0, "value": 0.0}, {"name": "AVGO", "amount": 1, "value": 90.89632415771484}, {"name": "AMZN", "amount": 0, "value": 0.0}], "date": "2015-05-05"}, {"funds": 9912.676155090332, "stocksHeld": [{"name": "ADBE", "amount": 0, "value": 0.0}, {"name": "MSFT", "amount": 0, "value": 0.0}, {"name": "AVGO", "amount": 1, "value": 90.89632415771484}, {"name": "AMZN", "amount": 0, "value": 0.0}], "date": "2015-05-05"}, {"funds": 9838.196151733398, "stocksHeld": [{"name": "ADBE", "amount": 1, "value": 74.4800033569336}, {"name": "MSFT", "amount": 0, "value": 0.0}, {"name": "AVGO", "amount": 1, "value": 90.88851165771484}, {"name": "AMZN", "amount": 0, "value": 0.0}], "date": "2015-05-06"}, {"funds": 9838.196151733398, "stocksHeld": [{"name": "ADBE", "amount": 1, "value": 74.4800033569336}, {"name": "MSFT", "amount": 0, "value": 0.0}, {"name": "AVGO", "amount": 1, "value": 90.88851165771484}, {"name": "AMZN", "amount": 0, "value": 0.0}], "date": "2015-05-06"}, {"funds": 9838.196151733398, "stocksHeld": [{"name": "ADBE", "amount": 1, "value": 74.4800033569336}, {"name": "MSFT", "amount": 0, "value": 0.0}, {"name": "AVGO", "amount": 1, "value": 90.88851165771484}, {"name": "AMZN", "amount": 0, "value": 0.0}], "date": "2015-05-06"}, {"funds": 9838.196151733398, "stocksHeld": [{"name": "ADBE", "amount": 1, "value": 74.4800033569336}, {"name": "MSFT", "amount": 0, "value": 0.0}, {"name": "AVGO", "amount": 1, "value": 90.88851165771484}, {"name": "AMZN", "amount": 0, "value": 0.0}], "date": "2015-05-06"}, {"funds": 9838.196151733398, "stocksHeld": [{"name": "ADBE", "amount": 1, "value": 74.7300033569336}, {"name": "MSFT", "amount": 0, "value": 0.0}, {"name": "AVGO", "amount": 1, "value": 95.32476806640625}, {"name": "AMZN", "amount": 0, "value": 0.0}], "date": "2015-05-07"}, {"funds": 9838.196151733398, "stocksHeld": [{"name": "ADBE", "amount": 1, "value": 74.7300033569336}, {"name": "MSFT", "amount": 0, "value": 0.0}, {"name": "AVGO", "amount": 1, "value": 95.32476806640625}, {"name": "AMZN", "amount": 0, "value": 0.0}], "date": "2015-05-07"}, {"funds": 9838.196151733398, "stocksHeld": [{"name": "ADBE", "amount": 1, "value": 74.7300033569336}, {"name": "MSFT", "amount": 0, "value": 0.0}, {"name": "AVGO", "amount": 1, "value": 95.32476806640625}, {"name": "AMZN", "amount": 0, "value": 0.0}], "date": "2015-05-07"}, {"funds": 9838.196151733398, "stocksHeld": [{"name": "ADBE", "amount": 1, "value": 74.7300033569336}, {"name": "MSFT", "amount": 0, "value": 0.0}, {"name": "AVGO", "amount": 1, "value": 95.32476806640625}, {"name": "AMZN", "amount": 0, "value": 0.0}], "date": "2015-05-07"}, {"funds": 9838.196151733398, "stocksHeld": [{"name": "ADBE", "amount": 1, "value": 76.30999755859375}, {"name": "MSFT", "amount": 0, "value": 0.0}, {"name": "AVGO", "amount": 1, "value": 95.986328125}, {"name": "AMZN", "amount": 0, "value": 0.0}], "date": "2015-05-08"}, {"funds": 9838.196151733398, "stocksHeld": [{"name": "ADBE", "amount": 1, "value": 76.30999755859375}, {"name": "MSFT", "amount": 0, "value": 0.0}, {"name": "AVGO", "amount": 1, "value": 95.986328125}, {"name": "AMZN", "amount": 0, "value": 0.0}], "date": "2015-05-08"}, {"funds": 9934.182479858398, "stocksHeld": [{"name": "ADBE", "amount": 1, "value": 76.30999755859375}, {"name": "MSFT", "amount": 0, "value": 0.0}, {"name": "AVGO", "amount": 0, "value": 0.0}, {"name": "AMZN", "amount": 0, "value": 0.0}], "date": "2015-05-08"}, {"funds": 9934.182479858398, "stocksHeld": [{"name": "ADBE", "amount": 1, "value": 76.30999755859375}, {"name": "MSFT", "amount": 0, "value": 0.0}, {"name": "AVGO", "amount": 0, "value": 0.0}, {"name": "AMZN", "amount": 0, "value": 0.0}], "date": "2015-05-08"}, {"funds": 10010.972480773926, "stocksHeld": [{"name": "ADBE", "amount": 0, "value": 0.0}, {"name": "MSFT", "amount": 0, "value": 0.0}, {"name": "AVGO", "amount": 0, "value": 0.0}, {"name": "AMZN", "amount": 0, "value": 0.0}], "date": "2015-05-11"}, {"funds": 9969.616611480713, "stocksHeld": [{"name": "ADBE", "amount": 0, "value": 0.0}, {"name": "MSFT", "amount": 1, "value": 41.35586929321289}, {"name": "AVGO", "amount": 0, "value": 0.0}, {"name": "AMZN", "amount": 0, "value": 0.0}], "date": "2015-05-11"}, {"funds": 9969.616611480713, "stocksHeld": [{"name": "ADBE", "amount": 0, "value": 0.0}, {"name": "MSFT", "amount": 1, "value": 41.35586929321289}, {"name": "AVGO", "amount": 0, "value": 0.0}, {"name": "AMZN", "amount": 0, "value": 0.0}], "date": "2015-05-11"}, {"funds": 9969.616611480713, "stocksHeld": [{"name": "ADBE", "amount": 0, "value": 0.0}, {"name": "MSFT", "amount": 1, "value": 41.35586929321289}, {"name": "AVGO", "amount": 0, "value": 0.0}, {"name": "AMZN", "amount": 0, "value": 0.0}], "date": "2015-05-11"}, {"funds": 9969.616611480713, "stocksHeld": [{"name": "ADBE", "amount": 0, "value": 0.0}, {"name": "MSFT", "amount": 1, "value": 41.33840560913086}, {"name": "AVGO", "amount": 0, "value": 0.0}, {"name": "AMZN", "amount": 0, "value": 0.0}], "date": "2015-05-12"}, {"funds": 9969.616611480713, "stocksHeld": [{"name": "ADBE", "amount": 0, "value": 0.0}, {"name": "MSFT", "amount": 1, "value": 41.33840560913086}, {"name": "AVGO", "amount": 0, "value": 0.0}, {"name": "AMZN", "amount": 0, "value": 0.0}], "date": "2015-05-12"}, {"funds": 9969.616611480713, "stocksHeld": [{"name": "ADBE", "amount": 0, "value": 0.0}, {"name": "MSFT", "amount": 1, "value": 41.33840560913086}, {"name": "AVGO", "amount": 0, "value": 0.0}, {"name": "AMZN", "amount": 0, "value": 0.0}], "date": "2015-05-12"}, {"funds": 9969.616611480713, "stocksHeld": [{"name": "ADBE", "amount": 0, "value": 0.0}, {"name": "MSFT", "amount": 1, "value": 41.33840560913086}, {"name": "AVGO", "amount": 0, "value": 0.0}, {"name": "AMZN", "amount": 0, "value": 0.0}], "date": "2015-05-12"}, {"funds": 9969.616611480713, "stocksHeld": [{"name": "ADBE", "amount": 0, "value": 0.0}, {"name": "MSFT", "amount": 1, "value": 41.582855224609375}, {"name": "AVGO", "amount": 0, "value": 0.0}, {"name": "AMZN", "amount": 0, "value": 0.0}], "date": "2015-05-13"}, {"funds": 9969.616611480713, "stocksHeld": [{"name": "ADBE", "amount": 0, "value": 0.0}, {"name": "MSFT", "amount": 1, "value": 41.582855224609375}, {"name": "AVGO", "amount": 0, "value": 0.0}, {"name": "AMZN", "amount": 0, "value": 0.0}], "date": "2015-05-13"}, {"funds": 9969.616611480713, "stocksHeld": [{"name": "ADBE", "amount": 0, "value": 0.0}, {"name": "MSFT", "amount": 1, "value": 41.582855224609375}, {"name": "AVGO", "amount": 0, "value": 0.0}, {"name": "AMZN", "amount": 0, "value": 0.0}], "date": "2015-05-13"}, {"funds": 9948.273111343384, "stocksHeld": [{"name": "ADBE", "amount": 0, "value": 0.0}, {"name": "MSFT", "amount": 1, "value": 41.582855224609375}, {"name": "AVGO", "amount": 0, "value": 0.0}, {"name": "AMZN", "amount": 1, "value": 21.3435001373291}], "date": "2015-05-13"}, {"funds": 9948.273111343384, "stocksHeld": [{"name": "ADBE", "amount": 0, "value": 0.0}, {"name": "MSFT", "amount": 1, "value": 42.534481048583984}, {"name": "AVGO", "amount": 0, "value": 0.0}, {"name": "AMZN", "amount": 1, "value": 21.61400032043457}], "date": "2015-05-14"}, {"funds": 9948.273111343384, "stocksHeld": [{"name": "ADBE", "amount": 0, "value": 0.0}, {"name": "MSFT", "amount": 1, "value": 42.534481048583984}, {"name": "AVGO", "amount": 0, "value": 0.0}, {"name": "AMZN", "amount": 1, "value": 21.61400032043457}], "date": "2015-05-14"}, {"funds": 9948.273111343384, "stocksHeld": [{"name": "ADBE", "amount": 0, "value": 0.0}, {"name": "MSFT", "amount": 1, "value": 42.534481048583984}, {"name": "AVGO", "amount": 0, "value": 0.0}, {"name": "AMZN", "amount": 1, "value": 21.61400032043457}], "date": "2015-05-14"}, {"funds": 9948.273111343384, "stocksHeld": [{"name": "ADBE", "amount": 0, "value": 0.0}, {"name": "MSFT", "amount": 1, "value": 42.534481048583984}, {"name": "AVGO", "amount": 0, "value": 0.0}, {"name": "AMZN", "amount": 1, "value": 21.61400032043457}], "date": "2015-05-14"}, {"funds": 9948.273111343384, "stocksHeld": [{"name": "ADBE", "amount": 0, "value": 0.0}, {"name": "MSFT", "amount": 1, "value": 42.16778564453125}, {"name": "AVGO", "amount": 0, "value": 0.0}, {"name": "AMZN", "amount": 1, "value": 21.299999237060547}], "date": "2015-05-15"}, {"funds": 9948.273111343384, "stocksHeld": [{"name": "ADBE", "amount": 0, "value": 0.0}, {"name": "MSFT", "amount": 1, "value": 42.16778564453125}, {"name": "AVGO", "amount": 0, "value": 0.0}, {"name": "AMZN", "amount": 1, "value": 21.299999237060547}], "date": "2015-05-15"}, {"funds": 9948.273111343384, "stocksHeld": [{"name": "ADBE", "amount": 0, "value": 0.0}, {"name": "MSFT", "amount": 1, "value": 42.16778564453125}, {"name": "AVGO", "amount": 0, "value": 0.0}, {"name": "AMZN", "amount": 1, "value": 21.299999237060547}], "date": "2015-05-15"}, {"funds": 9948.273111343384, "stocksHeld": [{"name": "ADBE", "amount": 0, "value": 0.0}, {"name": "MSFT", "amount": 1, "value": 42.16778564453125}, {"name": "AVGO", "amount": 0, "value": 0.0}, {"name": "AMZN", "amount": 1, "value": 21.299999237060547}], "date": "2015-05-15"}, {"funds": 9948.273111343384, "stocksHeld": [{"name": "ADBE", "amount": 0, "value": 0.0}, {"name": "MSFT", "amount": 1, "value": 41.91461181640625}, {"name": "AVGO", "amount": 0, "value": 0.0}, {"name": "AMZN", "amount": 1, "value": 21.261999130249023}], "date": "2015-05-18"}, {"funds": 9948.273111343384, "stocksHeld": [{"name": "ADBE", "amount": 0, "value": 0.0}, {"name": "MSFT", "amount": 1, "value": 41.91461181640625}, {"name": "AVGO", "amount": 0, "value": 0.0}, {"name": "AMZN", "amount": 1, "value": 21.261999130249023}], "date": "2015-05-18"}, {"funds": 9948.273111343384, "stocksHeld": [{"name": "ADBE", "amount": 0, "value": 0.0}, {"name": "MSFT", "amount": 1, "value": 41.91461181640625}, {"name": "AVGO", "amount": 0, "value": 0.0}, {"name": "AMZN", "amount": 1, "value": 21.261999130249023}], "date": "2015-05-18"}, {"funds": 9948.273111343384, "stocksHeld": [{"name": "ADBE", "amount": 0, "value": 0.0}, {"name": "MSFT", "amount": 1, "value": 41.91461181640625}, {"name": "AVGO", "amount": 0, "value": 0.0}, {"name": "AMZN", "amount": 1, "value": 21.261999130249023}], "date": "2015-05-18"}, {"funds": 9948.273111343384, "stocksHeld": [{"name": "ADBE", "amount": 0, "value": 0.0}, {"name": "MSFT", "amount": 1, "value": 41.809173583984375}, {"name": "AVGO", "amount": 0, "value": 0.0}, {"name": "AMZN", "amount": 1, "value": 21.085500717163086}], "date": "2015-05-19"}, {"funds": 9948.273111343384, "stocksHeld": [{"name": "ADBE", "amount": 0, "value": 0.0}, {"name": "MSFT", "amount": 1, "value": 41.809173583984375}, {"name": "AVGO", "amount": 0, "value": 0.0}, {"name": "AMZN", "amount": 1, "value": 21.085500717163086}], "date": "2015-05-19"}, {"funds": 9948.273111343384, "stocksHeld": [{"name": "ADBE", "amount": 0, "value": 0.0}, {"name": "MSFT", "amount": 1, "value": 41.809173583984375}, {"name": "AVGO", "amount": 0, "value": 0.0}, {"name": "AMZN", "amount": 1, "value": 21.085500717163086}], "date": "2015-05-19"}, {"funds": 9948.273111343384, "stocksHeld": [{"name": "ADBE", "amount": 0, "value": 0.0}, {"name": "MSFT", "amount": 1, "value": 41.809173583984375}, {"name": "AVGO", "amount": 0, "value": 0.0}, {"name": "AMZN", "amount": 1, "value": 21.085500717163086}], "date": "2015-05-19"}, {"funds": 9948.273111343384, "stocksHeld": [{"name": "ADBE", "amount": 0, "value": 0.0}, {"name": "MSFT", "amount": 1, "value": 41.809173583984375}, {"name": "AVGO", "amount": 0, "value": 0.0}, {"name": "AMZN", "amount": 1, "value": 21.19300079345703}], "date": "2015-05-20"}, {"funds": 9948.273111343384, "stocksHeld": [{"name": "ADBE", "amount": 0, "value": 0.0}, {"name": "MSFT", "amount": 1, "value": 41.809173583984375}, {"name": "AVGO", "amount": 0, "value": 0.0}, {"name": "AMZN", "amount": 1, "value": 21.19300079345703}], "date": "2015-05-20"}, {"funds": 9948.273111343384, "stocksHeld": [{"name": "ADBE", "amount": 0, "value": 0.0}, {"name": "MSFT", "amount": 1, "value": 41.809173583984375}, {"name": "AVGO", "amount": 0, "value": 0.0}, {"name": "AMZN", "amount": 1, "value": 21.19300079345703}], "date": "2015-05-20"}, {"funds": 9948.273111343384, "stocksHeld": [{"name": "ADBE", "amount": 0, "value": 0.0}, {"name": "MSFT", "amount": 1, "value": 41.809173583984375}, {"name": "AVGO", "amount": 0, "value": 0.0}, {"name": "AMZN", "amount": 1, "value": 21.19300079345703}], "date": "2015-05-20"}, {"funds": 9948.273111343384, "stocksHeld": [{"name": "ADBE", "amount": 0, "value": 0.0}, {"name": "MSFT", "amount": 1, "value": 41.6685791015625}, {"name": "AVGO", "amount": 0, "value": 0.0}, {"name": "AMZN", "amount": 1, "value": 21.581499099731445}], "date": "2015-05-21"}, {"funds": 9948.273111343384, "stocksHeld": [{"name": "ADBE", "amount": 0, "value": 0.0}, {"name": "MSFT", "amount": 1, "value": 41.6685791015625}, {"name": "AVGO", "amount": 0, "value": 0.0}, {"name": "AMZN", "amount": 1, "value": 21.581499099731445}], "date": "2015-05-21"}, {"funds": 9948.273111343384, "stocksHeld": [{"name": "ADBE", "amount": 0, "value": 0.0}, {"name": "MSFT", "amount": 1, "value": 41.6685791015625}, {"name": "AVGO", "amount": 0, "value": 0.0}, {"name": "AMZN", "amount": 1, "value": 21.581499099731445}], "date": "2015-05-21"}, {"funds": 9948.273111343384, "stocksHeld": [{"name": "ADBE", "amount": 0, "value": 0.0}, {"name": "MSFT", "amount": 1, "value": 41.6685791015625}, {"name": "AVGO", "amount": 0, "value": 0.0}, {"name": "AMZN", "amount": 1, "value": 21.581499099731445}], "date": "2015-05-21"}, {"funds": 9948.273111343384, "stocksHeld": [{"name": "ADBE", "amount": 0, "value": 0.0}, {"name": "MSFT", "amount": 1, "value": 41.21164321899414}, {"name": "AVGO", "amount": 0, "value": 0.0}, {"name": "AMZN", "amount": 1, "value": 21.381500244140625}], "date": "2015-05-22"}, {"funds": 9948.273111343384, "stocksHeld": [{"name": "ADBE", "amount": 0, "value": 0.0}, {"name": "MSFT", "amount": 1, "value": 41.21164321899414}, {"name": "AVGO", "amount": 0, "value": 0.0}, {"name": "AMZN", "amount": 1, "value": 21.381500244140625}], "date": "2015-05-22"}, {"funds": 9948.273111343384, "stocksHeld": [{"name": "ADBE", "amount": 0, "value": 0.0}, {"name": "MSFT", "amount": 1, "value": 41.21164321899414}, {"name": "AVGO", "amount": 0, "value": 0.0}, {"name": "AMZN", "amount": 1, "value": 21.381500244140625}], "date": "2015-05-22"}, {"funds": 9948.273111343384, "stocksHeld": [{"name": "ADBE", "amount": 0, "value": 0.0}, {"name": "MSFT", "amount": 1, "value": 41.21164321899414}, {"name": "AVGO", "amount": 0, "value": 0.0}, {"name": "AMZN", "amount": 1, "value": 21.381500244140625}], "date": "2015-05-22"}, {"funds": 9948.273111343384, "stocksHeld": [{"name": "ADBE", "amount": 0, "value": 0.0}, {"name": "MSFT", "amount": 1, "value": 40.939247131347656}, {"name": "AVGO", "amount": 0, "value": 0.0}, {"name": "AMZN", "amount": 1, "value": 21.273500442504883}], "date": "2015-05-26"}, {"funds": 9948.273111343384, "stocksHeld": [{"name": "ADBE", "amount": 0, "value": 0.0}, {"name": "MSFT", "amount": 1, "value": 40.939247131347656}, {"name": "AVGO", "amount": 0, "value": 0.0}, {"name": "AMZN", "amount": 1, "value": 21.273500442504883}], "date": "2015-05-26"}, {"funds": 9948.273111343384, "stocksHeld": [{"name": "ADBE", "amount": 0, "value": 0.0}, {"name": "MSFT", "amount": 1, "value": 40.939247131347656}, {"name": "AVGO", "amount": 0, "value": 0.0}, {"name": "AMZN", "amount": 1, "value": 21.273500442504883}], "date": "2015-05-26"}, {"funds": 9948.273111343384, "stocksHeld": [{"name": "ADBE", "amount": 0, "value": 0.0}, {"name": "MSFT", "amount": 1, "value": 40.939247131347656}, {"name": "AVGO", "amount": 0, "value": 0.0}, {"name": "AMZN", "amount": 1, "value": 21.273500442504883}], "date": "2015-05-26"}, {"funds": 9948.273111343384, "stocksHeld": [{"name": "ADBE", "amount": 0, "value": 0.0}, {"name": "MSFT", "amount": 1, "value": 41.83552551269531}, {"name": "AVGO", "amount": 0, "value": 0.0}, {"name": "AMZN", "amount": 1, "value": 21.570999145507812}], "date": "2015-05-27"}, {"funds": 9948.273111343384, "stocksHeld": [{"name": "ADBE", "amount": 0, "value": 0.0}, {"name": "MSFT", "amount": 1, "value": 41.83552551269531}, {"name": "AVGO", "amount": 0, "value": 0.0}, {"name": "AMZN", "amount": 1, "value": 21.570999145507812}], "date": "2015-05-27"}, {"funds": 9948.273111343384, "stocksHeld": [{"name": "ADBE", "amount": 0, "value": 0.0}, {"name": "MSFT", "amount": 1, "value": 41.83552551269531}, {"name": "AVGO", "amount": 0, "value": 0.0}, {"name": "AMZN", "amount": 1, "value": 21.570999145507812}], "date": "2015-05-27"}, {"funds": 9948.273111343384, "stocksHeld": [{"name": "ADBE", "amount": 0, "value": 0.0}, {"name": "MSFT", "amount": 1, "value": 41.83552551269531}, {"name": "AVGO", "amount": 0, "value": 0.0}, {"name": "AMZN", "amount": 1, "value": 21.570999145507812}], "date": "2015-05-27"}, {"funds": 9948.273111343384, "stocksHeld": [{"name": "ADBE", "amount": 0, "value": 0.0}, {"name": "MSFT", "amount": 1, "value": 41.694923400878906}, {"name": "AVGO", "amount": 0, "value": 0.0}, {"name": "AMZN", "amount": 1, "value": 21.328500747680664}], "date": "2015-05-28"}, {"funds": 9948.273111343384, "stocksHeld": [{"name": "ADBE", "amount": 0, "value": 0.0}, {"name": "MSFT", "amount": 1, "value": 41.694923400878906}, {"name": "AVGO", "amount": 0, "value": 0.0}, {"name": "AMZN", "amount": 1, "value": 21.328500747680664}], "date": "2015-05-28"}, {"funds": 9948.273111343384, "stocksHeld": [{"name": "ADBE", "amount": 0, "value": 0.0}, {"name": "MSFT", "amount": 1, "value": 41.694923400878906}, {"name": "AVGO", "amount": 0, "value": 0.0}, {"name": "AMZN", "amount": 1, "value": 21.328500747680664}], "date": "2015-05-28"}, {"funds": 9948.273111343384, "stocksHeld": [{"name": "ADBE", "amount": 0, "value": 0.0}, {"name": "MSFT", "amount": 1, "value": 41.694923400878906}, {"name": "AVGO", "amount": 0, "value": 0.0}, {"name": "AMZN", "amount": 1, "value": 21.328500747680664}], "date": "2015-05-28"}, {"funds": 9948.273111343384, "stocksHeld": [{"name": "ADBE", "amount": 0, "value": 0.0}, {"name": "MSFT", "amount": 1, "value": 41.17649459838867}, {"name": "AVGO", "amount": 0, "value": 0.0}, {"name": "AMZN", "amount": 1, "value": 21.46150016784668}], "date": "2015-05-29"}, {"funds": 9948.273111343384, "stocksHeld": [{"name": "ADBE", "amount": 0, "value": 0.0}, {"name": "MSFT", "amount": 1, "value": 41.17649459838867}, {"name": "AVGO", "amount": 0, "value": 0.0}, {"name": "AMZN", "amount": 1, "value": 21.46150016784668}], "date": "2015-05-29"}, {"funds": 9948.273111343384, "stocksHeld": [{"name": "ADBE", "amount": 0, "value": 0.0}, {"name": "MSFT", "amount": 1, "value": 41.17649459838867}, {"name": "AVGO", "amount": 0, "value": 0.0}, {"name": "AMZN", "amount": 1, "value": 21.46150016784668}], "date": "2015-05-29"}, {"funds": 9948.273111343384, "stocksHeld": [{"name": "ADBE", "amount": 0, "value": 0.0}, {"name": "MSFT", "amount": 1, "value": 41.17649459838867}, {"name": "AVGO", "amount": 0, "value": 0.0}, {"name": "AMZN", "amount": 1, "value": 21.46150016784668}], "date": "2015-05-29"}, {"funds": 9948.273111343384, "stocksHeld": [{"name": "ADBE", "amount": 0, "value": 0.0}, {"name": "MSFT", "amount": 1, "value": 41.501609802246094}, {"name": "AVGO", "amount": 0, "value": 0.0}, {"name": "AMZN", "amount": 1, "value": 21.54599952697754}], "date": "2015-06-01"}, {"funds": 9948.273111343384, "stocksHeld": [{"name": "ADBE", "amount": 0, "value": 0.0}, {"name": "MSFT", "amount": 1, "value": 41.501609802246094}, {"name": "AVGO", "amount": 0, "value": 0.0}, {"name": "AMZN", "amount": 1, "value": 21.54599952697754}], "date": "2015-06-01"}, {"funds": 9948.273111343384, "stocksHeld": [{"name": "ADBE", "amount": 0, "value": 0.0}, {"name": "MSFT", "amount": 1, "value": 41.501609802246094}, {"name": "AVGO", "amount": 0, "value": 0.0}, {"name": "AMZN", "amount": 1, "value": 21.54599952697754}], "date": "2015-06-01"}, {"funds": 9948.273111343384, "stocksHeld": [{"name": "ADBE", "amount": 0, "value": 0.0}, {"name": "MSFT", "amount": 1, "value": 41.501609802246094}, {"name": "AVGO", "amount": 0, "value": 0.0}, {"name": "AMZN", "amount": 1, "value": 21.54599952697754}], "date": "2015-06-01"}, {"funds": 9948.273111343384, "stocksHeld": [{"name": "ADBE", "amount": 0, "value": 0.0}, {"name": "MSFT", "amount": 1, "value": 41.229209899902344}, {"name": "AVGO", "amount": 0, "value": 0.0}, {"name": "AMZN", "amount": 1, "value": 21.54949951171875}], "date": "2015-06-02"}, {"funds": 9948.273111343384, "stocksHeld": [{"name": "ADBE", "amount": 0, "value": 0.0}, {"name": "MSFT", "amount": 1, "value": 41.229209899902344}, {"name": "AVGO", "amount": 0, "value": 0.0}, {"name": "AMZN", "amount": 1, "value": 21.54949951171875}], "date": "2015-06-02"}, {"funds": 9948.273111343384, "stocksHeld": [{"name": "ADBE", "amount": 0, "value": 0.0}, {"name": "MSFT", "amount": 1, "value": 41.229209899902344}, {"name": "AVGO", "amount": 0, "value": 0.0}, {"name": "AMZN", "amount": 1, "value": 21.54949951171875}], "date": "2015-06-02"}, {"funds": 9948.273111343384, "stocksHeld": [{"name": "ADBE", "amount": 0, "value": 0.0}, {"name": "MSFT", "amount": 1, "value": 41.229209899902344}, {"name": "AVGO", "amount": 0, "value": 0.0}, {"name": "AMZN", "amount": 1, "value": 21.54949951171875}], "date": "2015-06-02"}, {"funds": 9948.273111343384, "stocksHeld": [{"name": "ADBE", "amount": 0, "value": 0.0}, {"name": "MSFT", "amount": 1, "value": 41.16771697998047}, {"name": "AVGO", "amount": 0, "value": 0.0}, {"name": "AMZN", "amount": 1, "value": 21.829500198364258}], "date": "2015-06-03"}, {"funds": 9948.273111343384, "stocksHeld": [{"name": "ADBE", "amount": 0, "value": 0.0}, {"name": "MSFT", "amount": 1, "value": 41.16771697998047}, {"name": "AVGO", "amount": 0, "value": 0.0}, {"name": "AMZN", "amount": 1, "value": 21.829500198364258}], "date": "2015-06-03"}, {"funds": 9948.273111343384, "stocksHeld": [{"name": "ADBE", "amount": 0, "value": 0.0}, {"name": "MSFT", "amount": 1, "value": 41.16771697998047}, {"name": "AVGO", "amount": 0, "value": 0.0}, {"name": "AMZN", "amount": 1, "value": 21.829500198364258}], "date": "2015-06-03"}, {"funds": 9948.273111343384, "stocksHeld": [{"name": "ADBE", "amount": 0, "value": 0.0}, {"name": "MSFT", "amount": 1, "value": 41.16771697998047}, {"name": "AVGO", "amount": 0, "value": 0.0}, {"name": "AMZN", "amount": 1, "value": 21.829500198364258}], "date": "2015-06-03"}, {"funds": 9869.523111343384, "stocksHeld": [{"name": "ADBE", "amount": 1, "value": 78.75}, {"name": "MSFT", "amount": 1, "value": 40.73714828491211}, {"name": "AVGO", "amount": 0, "value": 0.0}, {"name": "AMZN", "amount": 1, "value": 21.538999557495117}], "date": "2015-06-04"}, {"funds": 9869.523111343384, "stocksHeld": [{"name": "ADBE", "amount": 1, "value": 78.75}, {"name": "MSFT", "amount": 1, "value": 40.73714828491211}, {"name": "AVGO", "amount": 0, "value": 0.0}, {"name": "AMZN", "amount": 1, "value": 21.538999557495117}], "date": "2015-06-04"}, {"funds": 9869.523111343384, "stocksHeld": [{"name": "ADBE", "amount": 1, "value": 78.75}, {"name": "MSFT", "amount": 1, "value": 40.73714828491211}, {"name": "AVGO", "amount": 0, "value": 0.0}, {"name": "AMZN", "amount": 1, "value": 21.538999557495117}], "date": "2015-06-04"}, {"funds": 9869.523111343384, "stocksHeld": [{"name": "ADBE", "amount": 1, "value": 78.75}, {"name": "MSFT", "amount": 1, "value": 40.73714828491211}, {"name": "AVGO", "amount": 0, "value": 0.0}, {"name": "AMZN", "amount": 1, "value": 21.538999557495117}], "date": "2015-06-04"}, {"funds": 9869.523111343384, "stocksHeld": [{"name": "ADBE", "amount": 1, "value": 78.86000061035156}, {"name": "MSFT", "amount": 1, "value": 40.54381561279297}, {"name": "AVGO", "amount": 0, "value": 0.0}, {"name": "AMZN", "amount": 1, "value": 21.34749984741211}], "date": "2015-06-05"}, {"funds": 9869.523111343384, "stocksHeld": [{"name": "ADBE", "amount": 1, "value": 78.86000061035156}, {"name": "MSFT", "amount": 1, "value": 40.54381561279297}, {"name": "AVGO", "amount": 0, "value": 0.0}, {"name": "AMZN", "amount": 1, "value": 21.34749984741211}], "date": "2015-06-05"}, {"funds": 9869.523111343384, "stocksHeld": [{"name": "ADBE", "amount": 1, "value": 78.86000061035156}, {"name": "MSFT", "amount": 1, "value": 40.54381561279297}, {"name": "AVGO", "amount": 0, "value": 0.0}, {"name": "AMZN", "amount": 1, "value": 21.34749984741211}], "date": "2015-06-05"}, {"funds": 9869.523111343384, "stocksHeld": [{"name": "ADBE", "amount": 1, "value": 78.86000061035156}, {"name": "MSFT", "amount": 1, "value": 40.54381561279297}, {"name": "AVGO", "amount": 0, "value": 0.0}, {"name": "AMZN", "amount": 1, "value": 21.34749984741211}], "date": "2015-06-05"}, {"funds": 9869.523111343384, "stocksHeld": [{"name": "ADBE", "amount": 1, "value": 78.16000366210938}, {"name": "MSFT", "amount": 1, "value": 40.183555603027344}, {"name": "AVGO", "amount": 0, "value": 0.0}, {"name": "AMZN", "amount": 1, "value": 21.174999237060547}], "date": "2015-06-08"}, {"funds": 9869.523111343384, "stocksHeld": [{"name": "ADBE", "amount": 1, "value": 78.16000366210938}, {"name": "MSFT", "amount": 1, "value": 40.183555603027344}, {"name": "AVGO", "amount": 0, "value": 0.0}, {"name": "AMZN", "amount": 1, "value": 21.174999237060547}], "date": "2015-06-08"}, {"funds": 9869.523111343384, "stocksHeld": [{"name": "ADBE", "amount": 1, "value": 78.16000366210938}, {"name": "MSFT", "amount": 1, "value": 40.183555603027344}, {"name": "AVGO", "amount": 0, "value": 0.0}, {"name": "AMZN", "amount": 1, "value": 21.174999237060547}], "date": "2015-06-08"}, {"funds": 9869.523111343384, "stocksHeld": [{"name": "ADBE", "amount": 1, "value": 78.16000366210938}, {"name": "MSFT", "amount": 1, "value": 40.183555603027344}, {"name": "AVGO", "amount": 0, "value": 0.0}, {"name": "AMZN", "amount": 1, "value": 21.174999237060547}], "date": "2015-06-08"}, {"funds": 9869.523111343384, "stocksHeld": [{"name": "ADBE", "amount": 1, "value": 77.9000015258789}, {"name": "MSFT", "amount": 1, "value": 40.113258361816406}, {"name": "AVGO", "amount": 0, "value": 0.0}, {"name": "AMZN", "amount": 1, "value": 21.27400016784668}], "date": "2015-06-09"}, {"funds": 9869.523111343384, "stocksHeld": [{"name": "ADBE", "amount": 1, "value": 77.9000015258789}, {"name": "MSFT", "amount": 1, "value": 40.113258361816406}, {"name": "AVGO", "amount": 0, "value": 0.0}, {"name": "AMZN", "amount": 1, "value": 21.27400016784668}], "date": "2015-06-09"}, {"funds": 9869.523111343384, "stocksHeld": [{"name": "ADBE", "amount": 1, "value": 77.9000015258789}, {"name": "MSFT", "amount": 1, "value": 40.113258361816406}, {"name": "AVGO", "amount": 0, "value": 0.0}, {"name": "AMZN", "amount": 1, "value": 21.27400016784668}], "date": "2015-06-09"}, {"funds": 9869.523111343384, "stocksHeld": [{"name": "ADBE", "amount": 1, "value": 77.9000015258789}, {"name": "MSFT", "amount": 1, "value": 40.113258361816406}, {"name": "AVGO", "amount": 0, "value": 0.0}, {"name": "AMZN", "amount": 1, "value": 21.27400016784668}], "date": "2015-06-09"}, {"funds": 9869.523111343384, "stocksHeld": [{"name": "ADBE", "amount": 1, "value": 79.55999755859375}, {"name": "MSFT", "amount": 1, "value": 40.95680618286133}, {"name": "AVGO", "amount": 0, "value": 0.0}, {"name": "AMZN", "amount": 1, "value": 21.53849983215332}], "date": "2015-06-10"}, {"funds": 9869.523111343384, "stocksHeld": [{"name": "ADBE", "amount": 1, "value": 79.55999755859375}, {"name": "MSFT", "amount": 1, "value": 40.95680618286133}, {"name": "AVGO", "amount": 0, "value": 0.0}, {"name": "AMZN", "amount": 1, "value": 21.53849983215332}], "date": "2015-06-10"}, {"funds": 9758.336786270142, "stocksHeld": [{"name": "ADBE", "amount": 1, "value": 79.55999755859375}, {"name": "MSFT", "amount": 1, "value": 40.95680618286133}, {"name": "AVGO", "amount": 1, "value": 111.18632507324219}, {"name": "AMZN", "amount": 1, "value": 21.53849983215332}], "date": "2015-06-10"}, {"funds": 9758.336786270142, "stocksHeld": [{"name": "ADBE", "amount": 1, "value": 79.55999755859375}, {"name": "MSFT", "amount": 1, "value": 40.95680618286133}, {"name": "AVGO", "amount": 1, "value": 111.18632507324219}, {"name": "AMZN", "amount": 1, "value": 21.53849983215332}], "date": "2015-06-10"}, {"funds": 9758.336786270142, "stocksHeld": [{"name": "ADBE", "amount": 1, "value": 79.6500015258789}, {"name": "MSFT", "amount": 1, "value": 40.80744171142578}, {"name": "AVGO", "amount": 1, "value": 110.50920104980469}, {"name": "AMZN", "amount": 1, "value": 21.648500442504883}], "date": "2015-06-11"}, {"funds": 9758.336786270142, "stocksHeld": [{"name": "ADBE", "amount": 1, "value": 79.6500015258789}, {"name": "MSFT", "amount": 1, "value": 40.80744171142578}, {"name": "AVGO", "amount": 1, "value": 110.50920104980469}, {"name": "AMZN", "amount": 1, "value": 21.648500442504883}], "date": "2015-06-11"}, {"funds": 9758.336786270142, "stocksHeld": [{"name": "ADBE", "amount": 1, "value": 79.6500015258789}, {"name": "MSFT", "amount": 1, "value": 40.80744171142578}, {"name": "AVGO", "amount": 1, "value": 110.50920104980469}, {"name": "AMZN", "amount": 1, "value": 21.648500442504883}], "date": "2015-06-11"}, {"funds": 9758.336786270142, "stocksHeld": [{"name": "ADBE", "amount": 1, "value": 79.6500015258789}, {"name": "MSFT", "amount": 1, "value": 40.80744171142578}, {"name": "AVGO", "amount": 1, "value": 110.50920104980469}, {"name": "AMZN", "amount": 1, "value": 21.648500442504883}], "date": "2015-06-11"}, {"funds": 9758.336786270142, "stocksHeld": [{"name": "ADBE", "amount": 1, "value": 79.86000061035156}, {"name": "MSFT", "amount": 1, "value": 40.39443588256836}, {"name": "AVGO", "amount": 1, "value": 109.3261947631836}, {"name": "AMZN", "amount": 1, "value": 21.496000289916992}], "date": "2015-06-12"}, {"funds": 9758.336786270142, "stocksHeld": [{"name": "ADBE", "amount": 1, "value": 79.86000061035156}, {"name": "MSFT", "amount": 1, "value": 40.39443588256836}, {"name": "AVGO", "amount": 1, "value": 109.3261947631836}, {"name": "AMZN", "amount": 1, "value": 21.496000289916992}], "date": "2015-06-12"}, {"funds": 9758.336786270142, "stocksHeld": [{"name": "ADBE", "amount": 1, "value": 79.86000061035156}, {"name": "MSFT", "amount": 1, "value": 40.39443588256836}, {"name": "AVGO", "amount": 1, "value": 109.3261947631836}, {"name": "AMZN", "amount": 1, "value": 21.496000289916992}], "date": "2015-06-12"}, {"funds": 9758.336786270142, "stocksHeld": [{"name": "ADBE", "amount": 1, "value": 79.86000061035156}, {"name": "MSFT", "amount": 1, "value": 40.39443588256836}, {"name": "AVGO", "amount": 1, "value": 109.3261947631836}, {"name": "AMZN", "amount": 1, "value": 21.496000289916992}], "date": "2015-06-12"}, {"funds": 9758.336786270142, "stocksHeld": [{"name": "ADBE", "amount": 1, "value": 78.9000015258789}, {"name": "MSFT", "amount": 1, "value": 39.963863372802734}, {"name": "AVGO", "amount": 1, "value": 111.38862609863281}, {"name": "AMZN", "amount": 1, "value": 21.183500289916992}], "date": "2015-06-15"}, {"funds": 9758.336786270142, "stocksHeld": [{"name": "ADBE", "amount": 1, "value": 78.9000015258789}, {"name": "MSFT", "amount": 1, "value": 39.963863372802734}, {"name": "AVGO", "amount": 1, "value": 111.38862609863281}, {"name": "AMZN", "amount": 1, "value": 21.183500289916992}], "date": "2015-06-15"}, {"funds": 9758.336786270142, "stocksHeld": [{"name": "ADBE", "amount": 1, "value": 78.9000015258789}, {"name": "MSFT", "amount": 1, "value": 39.963863372802734}, {"name": "AVGO", "amount": 1, "value": 111.38862609863281}, {"name": "AMZN", "amount": 1, "value": 21.183500289916992}], "date": "2015-06-15"}, {"funds": 9758.336786270142, "stocksHeld": [{"name": "ADBE", "amount": 1, "value": 78.9000015258789}, {"name": "MSFT", "amount": 1, "value": 39.963863372802734}, {"name": "AVGO", "amount": 1, "value": 111.38862609863281}, {"name": "AMZN", "amount": 1, "value": 21.183500289916992}], "date": "2015-06-15"}, {"funds": 9758.336786270142, "stocksHeld": [{"name": "ADBE", "amount": 1, "value": 79.94000244140625}, {"name": "MSFT", "amount": 1, "value": 40.271427154541016}, {"name": "AVGO", "amount": 1, "value": 110.50920104980469}, {"name": "AMZN", "amount": 1, "value": 21.363000869750977}], "date": "2015-06-16"}, {"funds": 9758.336786270142, "stocksHeld": [{"name": "ADBE", "amount": 1, "value": 79.94000244140625}, {"name": "MSFT", "amount": 1, "value": 40.271427154541016}, {"name": "AVGO", "amount": 1, "value": 110.50920104980469}, {"name": "AMZN", "amount": 1, "value": 21.363000869750977}], "date": "2015-06-16"}, {"funds": 9758.336786270142, "stocksHeld": [{"name": "ADBE", "amount": 1, "value": 79.94000244140625}, {"name": "MSFT", "amount": 1, "value": 40.271427154541016}, {"name": "AVGO", "amount": 1, "value": 110.50920104980469}, {"name": "AMZN", "amount": 1, "value": 21.363000869750977}], "date": "2015-06-16"}, {"funds": 9758.336786270142, "stocksHeld": [{"name": "ADBE", "amount": 1, "value": 79.94000244140625}, {"name": "MSFT", "amount": 1, "value": 40.271427154541016}, {"name": "AVGO", "amount": 1, "value": 110.50920104980469}, {"name": "AMZN", "amount": 1, "value": 21.363000869750977}], "date": "2015-06-16"}, {"funds": 9758.336786270142, "stocksHeld": [{"name": "ADBE", "amount": 1, "value": 77.91000366210938}, {"name": "MSFT", "amount": 1, "value": 40.39443588256836}, {"name": "AVGO", "amount": 1, "value": 109.80673217773438}, {"name": "AMZN", "amount": 1, "value": 21.390499114990234}], "date": "2015-06-17"}, {"funds": 9758.336786270142, "stocksHeld": [{"name": "ADBE", "amount": 1, "value": 77.91000366210938}, {"name": "MSFT", "amount": 1, "value": 40.39443588256836}, {"name": "AVGO", "amount": 1, "value": 109.80673217773438}, {"name": "AMZN", "amount": 1, "value": 21.390499114990234}], "date": "2015-06-17"}, {"funds": 9758.336786270142, "stocksHeld": [{"name": "ADBE", "amount": 1, "value": 77.91000366210938}, {"name": "MSFT", "amount": 1, "value": 40.39443588256836}, {"name": "AVGO", "amount": 1, "value": 109.80673217773438}, {"name": "AMZN", "amount": 1, "value": 21.390499114990234}], "date": "2015-06-17"}, {"funds": 9758.336786270142, "stocksHeld": [{"name": "ADBE", "amount": 1, "value": 77.91000366210938}, {"name": "MSFT", "amount": 1, "value": 40.39443588256836}, {"name": "AVGO", "amount": 1, "value": 109.80673217773438}, {"name": "AMZN", "amount": 1, "value": 21.390499114990234}], "date": "2015-06-17"}, {"funds": 9758.336786270142, "stocksHeld": [{"name": "ADBE", "amount": 1, "value": 79.38999938964844}, {"name": "MSFT", "amount": 1, "value": 41.05347442626953}, {"name": "AVGO", "amount": 1, "value": 111.6096420288086}, {"name": "AMZN", "amount": 1, "value": 21.969499588012695}], "date": "2015-06-18"}, {"funds": 9758.336786270142, "stocksHeld": [{"name": "ADBE", "amount": 1, "value": 79.38999938964844}, {"name": "MSFT", "amount": 1, "value": 41.05347442626953}, {"name": "AVGO", "amount": 1, "value": 111.6096420288086}, {"name": "AMZN", "amount": 1, "value": 21.969499588012695}], "date": "2015-06-18"}, {"funds": 9758.336786270142, "stocksHeld": [{"name": "ADBE", "amount": 1, "value": 79.38999938964844}, {"name": "MSFT", "amount": 1, "value": 41.05347442626953}, {"name": "AVGO", "amount": 1, "value": 111.6096420288086}, {"name": "AMZN", "amount": 1, "value": 21.969499588012695}], "date": "2015-06-18"}, {"funds": 9758.336786270142, "stocksHeld": [{"name": "ADBE", "amount": 1, "value": 79.38999938964844}, {"name": "MSFT", "amount": 1, "value": 41.05347442626953}, {"name": "AVGO", "amount": 1, "value": 111.6096420288086}, {"name": "AMZN", "amount": 1, "value": 21.969499588012695}], "date": "2015-06-18"}], "strategyName": "MACDDM"}